speculators/__init__.py
speculators/__main__.py
speculators/config.py
speculators/model.py
speculators/version.py
speculators/convert/__init__.py
speculators/convert/entrypoints.py
speculators/convert/eagle/__init__.py
speculators/convert/eagle/eagle3_converter.py
speculators/convert/eagle/eagle_converter.py
speculators/convert/eagle/utils.py
speculators/models/__init__.py
speculators/models/eagle.py
speculators/models/eagle3.py
speculators/models/independent.py
speculators/models/mlp.py
speculators/proposals/__init__.py
speculators/proposals/dynamic_tree.py
speculators/proposals/greedy.py
speculators/proposals/sampling.py
speculators/proposals/static_tree.py
speculators/utils/__init__.py
speculators/utils/auto_importer.py
speculators/utils/loading.py
speculators/utils/pydantic_utils.py
speculators/utils/registry.py
speculators-0.2.0.dist-info/licenses/LICENSE
speculators-0.2.0.dist-info/METADATA
speculators-0.2.0.dist-info/WHEEL
speculators-0.2.0.dist-info/entry_points.txt
speculators-0.2.0.dist-info/top_level.txt
speculators-0.2.0.dist-info/RECORD
