Metadata-Version: 2.4
Name: speculators
Version: 0.2.0
Summary: A unified library for creating, representing, and storing speculative decoding algorithms for LLM serving such as in vLLM.
Author: Red Hat
License-Expression: Apache-2.0
Project-URL: homepage, https://github.com/neuralmagic/speculators
Project-URL: source, https://github.com/neuralmagic/speculators
Project-URL: issues, https://github.com/neuralmagic/speculators/issues
Keywords: speculative decoding,transformers,llm,inference,vllm,machine learning,deep learning,nlp,language models,serving,standard format,productization,decoding algorithms,inference server
Requires-Python: >=3.10
License-File: LICENSE
Requires-Dist: accelerate
Requires-Dist: click
Requires-Dist: datasets
Requires-Dist: deepspeed
Requires-Dist: httpx[http2]
Requires-Dist: huggingface-hub
Requires-Dist: loguru
Requires-Dist: numpy
Requires-Dist: protobuf
Requires-Dist: pydantic>=2.0.0
Requires-Dist: pydantic-settings>=2.0.0
Requires-Dist: pyyaml>=6.0.0
Requires-Dist: safetensors
Requires-Dist: torch
Requires-Dist: transformers
Requires-Dist: typer-slim>=0.12.0
Provides-Extra: dev
Requires-Dist: build>=1.0.0; extra == "dev"
Requires-Dist: setuptools>=61.0; extra == "dev"
Requires-Dist: setuptools-git-versioning<3,>=2.0; extra == "dev"
Requires-Dist: mike~=2.1.3; extra == "dev"
Requires-Dist: mkdocs~=1.6.1; extra == "dev"
Requires-Dist: mkdocs-material[imaging]~=9.6.16; extra == "dev"
Requires-Dist: markdown~=3.8.2; extra == "dev"
Requires-Dist: pymdown-extensions~=10.16.1; extra == "dev"
Requires-Dist: mkdocs-section-index~=0.3.10; extra == "dev"
Requires-Dist: mkdocs-minify-plugin~=0.8.0; extra == "dev"
Requires-Dist: mkdocs-api-autonav~=0.3.1; extra == "dev"
Requires-Dist: mkdocstrings-python~=1.16.12; extra == "dev"
Requires-Dist: mkdocs-gen-files~=0.5.0; extra == "dev"
Requires-Dist: mkdocs-nav-weight~=0.2.0; extra == "dev"
Requires-Dist: pre-commit~=3.5.0; extra == "dev"
Requires-Dist: sphinx~=7.1.2; extra == "dev"
Requires-Dist: tox~=4.16.0; extra == "dev"
Requires-Dist: pytest~=8.2.2; extra == "dev"
Requires-Dist: pytest-asyncio~=0.23.8; extra == "dev"
Requires-Dist: pytest-cov~=5.0.0; extra == "dev"
Requires-Dist: pytest-mock~=3.14.0; extra == "dev"
Requires-Dist: pytest-rerunfailures~=14.0; extra == "dev"
Requires-Dist: respx~=0.22.0; extra == "dev"
Requires-Dist: mypy~=1.15.0; extra == "dev"
Requires-Dist: ruff~=0.14.1; extra == "dev"
Requires-Dist: mdformat~=0.7.17; extra == "dev"
Requires-Dist: mdformat-footnote~=0.1.1; extra == "dev"
Requires-Dist: mdformat-frontmatter~=2.0.8; extra == "dev"
Requires-Dist: mdformat-gfm~=0.3.6; extra == "dev"
Requires-Dist: types-click~=7.1.8; extra == "dev"
Requires-Dist: types-PyYAML~=6.0.1; extra == "dev"
Requires-Dist: types-requests~=2.32.0; extra == "dev"
Requires-Dist: types-toml; extra == "dev"
Requires-Dist: mkdocs-linkcheck~=1.0.6; extra == "dev"
Dynamic: license-file
